Metadata-Version: 2.1
Name: consoledraw
Version: 2.4.2
Summary: A python module to update the console without flashing.
Home-page: https://github.com/Matthias1590/ConsoleDraw
Author: Matthias Wijnsma
Author-email: matthiasx95@gmail.com
License: MIT
Platform: UNKNOWN
Requires-Python: >=3.6
